{
	"format_version": "1.8.0",
	"animations": {
		"animation.skeleton.emerge": {
			"animation_length": 1.5,
			"bones": {
				"waist": {
					"rotation": {
						"0.0": {
							"post": [0, 0, 0],
							"lerp_mode": "catmullrom"
						},
						"1.5": {
							"post": [0, 0, 0],
							"lerp_mode": "catmullrom"
						}
					},
					"position": {
						"0.0": {
							"post": [0, -40, 0],
							"lerp_mode": "catmullrom"
						},
						"1.5": {
							"post": [0, -40, 0],
							"lerp_mode": "catmullrom"
						}
					}
				},
				"body": {
					"rotation": {
						"0.0": {
							"post": [0, 0, 0],
							"lerp_mode": "catmullrom"
						},
						"0.3": {
							"post": [0, 0, 0],
							"lerp_mode": "catmullrom"
						},
						"0.7": {
							"post": [0, 0, 0],
							"lerp_mode": "catmullrom"
						},
						"1.0": {
							"post": [20, 0, 0],
							"lerp_mode": "catmullrom"
						},
						"1.2": {
							"post": [110, 0, 0],
							"lerp_mode": "catmullrom"
						},
						"1.5": {
							"post": [0, 0, 0],
							"lerp_mode": "catmullrom"
						}
					},
					"position": {
						"0.0": {
							"post": [0, 8, 0],
							"lerp_mode": "catmullrom"
						},
						"0.3": {
							"post": [0, 8, 0],
							"lerp_mode": "catmullrom"
						},
						"0.7": {
							"post": [0, 20, 0],
							"lerp_mode": "catmullrom"
						},
						"1.0": {
							"post": [0, 26, -4],
							"lerp_mode": "catmullrom"
						},
						"1.2": {
							"post": [0, 24.5, -11],
							"lerp_mode": "catmullrom"
						},
						"1.5": {
							"post": [0, 41, 0],
							"lerp_mode": "catmullrom"
						}
					}
				},
				"head": {
					"rotation": {
						"0.0": {
							"post": [0, 0, 0],
							"lerp_mode": "catmullrom"
						},
						"0.7": {
							"post": [50, 0, 0],
							"lerp_mode": "catmullrom"
						},
						"1.0": {
							"post": [-52.5, 0, 0],
							"lerp_mode": "catmullrom"
						},
						"1.2": {
							"post": [20, 0, 0],
							"lerp_mode": "catmullrom"
						},
						"1.5": {
							"post": [0, 0, 0],
							"lerp_mode": "catmullrom"
						}
					},
					"position": {
						"0.0": {
							"post": [0, 0, 0],
							"lerp_mode": "catmullrom"
						},
						"0.7": {
							"post": [0, 0, 0],
							"lerp_mode": "catmullrom"
						},
						"1.0": {
							"post": [0, 3, -1.5],
							"lerp_mode": "catmullrom"
						},
						"1.2": {
							"post": [0, 0.25, 0.5],
							"lerp_mode": "catmullrom"
						},
						"1.5": {
							"post": [0, 0, 0],
							"lerp_mode": "catmullrom"
						}
					}
				},
				"rightArm": {
					"rotation": {
						"0.0": {
							"post": [-180, 0, 0],
							"lerp_mode": "catmullrom"
						},
						"0.4": {
							"post": [-180, 0, 0],
							"lerp_mode": "catmullrom"
						},
						"0.7": {
							"post": [0, 0, 90],
							"lerp_mode": "catmullrom"
						},
						"1.0": {
							"post": [-90, -52.5, 90],
							"lerp_mode": "catmullrom"
						},
						"1.2": {
							"post": [-90, 20, 90],
							"lerp_mode": "catmullrom"
						},
						"1.5": {
							"post": [0, 0, 0],
							"lerp_mode": "catmullrom"
						}
					},
					"position": {
						"0.0": {
							"post": [0, 0, 0],
							"lerp_mode": "catmullrom"
						},
						"0.2": {
							"post": [0, 0, 0],
							"lerp_mode": "catmullrom"
						},
						"0.3": {
							"post": [0, 12, 0],
							"lerp_mode": "catmullrom"
						},
						"0.4": {
							"post": [0, 12, 0],
							"lerp_mode": "catmullrom"
						},
						"0.7": {
							"post": [-2, -1, 0],
							"lerp_mode": "catmullrom"
						},
						"1.0": {
							"post": [-2, 1.75, 0],
							"lerp_mode": "catmullrom"
						},
						"1.2": {
							"post": [-1, 1.75, 1.5],
							"lerp_mode": "catmullrom"
						},
						"1.5": {
							"post": [0, 0, 0],
							"lerp_mode": "catmullrom"
						}
					}
				},
				"leftArm": {
					"rotation": {
						"0.0": {
							"post": [-180, 0, 0],
							"lerp_mode": "catmullrom"
						},
						"0.4": {
							"post": [-180, 0, 0],
							"lerp_mode": "catmullrom"
						},
						"0.7": {
							"post": [0, 0, -90],
							"lerp_mode": "catmullrom"
						},
						"1.0": {
							"post": [-93.57333, 50.01429, -94.80129],
							"lerp_mode": "catmullrom"
						},
						"1.2": {
							"post": [-89.9414, -19.91415, -91.22991],
							"lerp_mode": "catmullrom"
						},
						"1.5": {
							"post": [0, 0, 0],
							"lerp_mode": "catmullrom"
						}
					},
					"position": {
						"0.0": {
							"post": [0, 0, 0],
							"lerp_mode": "catmullrom"
						},
						"0.1": {
							"post": [0, 0, 0],
							"lerp_mode": "catmullrom"
						},
						"0.2": {
							"post": [0, 12, 0],
							"lerp_mode": "catmullrom"
						},
						"0.4": {
							"post": [0, 12, 0],
							"lerp_mode": "catmullrom"
						},
						"0.7": {
							"post": [2, -1, 0],
							"lerp_mode": "catmullrom"
						},
						"1.0": {
							"post": [2, 1.7, 0],
							"lerp_mode": "catmullrom"
						},
						"1.2": {
							"post": [1, 1.7, 1.5],
							"lerp_mode": "catmullrom"
						},
						"1.5": {
							"post": [0, 0, 0],
							"lerp_mode": "catmullrom"
						}
					}
				},
				"rightLeg": {
					"rotation": {
						"0.0": [0, 0, 0],
						"1.0": [0, 0, 0],
						"1.1": [-110, 0, 0],
						"1.5": [0, 0, 0]
					},
					"position": {
						"0.0": [0, 0, 0],
						"1.0": [0, 0, 0],
						"1.5": [0, 0, 0]
					}
				},
				"leftLeg": {
					"rotation": {
						"0.0": [0, 0, 0],
						"1.0": [0, 0, 0],
						"1.1": [-110, 0, 0],
						"1.5": [0, 0, 0]
					},
					"position": {
						"0.0": [0, 0, 0],
						"1.0": [0, 0, 0],
						"1.5": [0, 0, 0]
					}
				}
			},
			"particle_effects": {
				"0.0": {
					"effect": "emerge",
					"pre_effect_script": "variable.dig_particle_texture_coordinate = query.surface_particle_texture_coordinate; variable.dig_particle_texture_size = query.surface_particle_texture_size; variable.dig_particle_color = query.surface_particle_color;"
				},
				"1.5": {
					"effect": "emerge",
					"pre_effect_script": "variable.dig_particle_texture_coordinate = query.surface_particle_texture_coordinate; variable.dig_particle_texture_size = query.surface_particle_texture_size; variable.dig_particle_color = query.surface_particle_color;"
				}
			}
		}
	}
}